{
  "products": [
    {
      "id": 1,
      "name": "Product001",
      "cost": 100,
      "quantity": 10000,
      "locationId": 1,
      "familyId": 1
    },
    {
      "id": 2,
      "name": "Product002",
      "cost": 200,
      "quantity": 20000,
      "locationId": 2,
      "familyId": 2
    },
    {
      "id": 3,
      "name": "Product003",
      "cost": 300,
      "quantity": 30000,
      "locationId": 3,
      "familyId": 3
    },
    {
      "id": 4,
      "name": "Product004",
      "cost": 400,
      "quantity": 40000,
      "locationId": 4,
      "familyId": 4
    }
  ]
}
